typico/__init__.py
typico/_xyz.py
typico/py.typed
typico/pyfield.py
typico/type_introspection.py
typico/utils.py
typico-0.0.2.dist-info/METADATA
typico-0.0.2.dist-info/WHEEL
typico-0.0.2.dist-info/licenses/LICENSE
typico-0.0.2.dist-info/RECORD
