Metadata-Version: 2.4
Name: typico
Version: 0.0.2
Summary: Type helpers and abstractions
Project-URL: Documentation, https://phil65.github.io/typico/
Project-URL: Source, https://github.com/phil65/typico
Project-URL: Issues, https://github.com/phil65/typico/issues
Project-URL: Discussions, https://github.com/phil65/typico/discussions
Project-URL: Code coverage, https://app.codecov.io/gh/phil65/typico
Author-email: Philipp Temminghoff <philipptemminghoff@googlemail.com>
License: MIT License
License-File: LICENSE
Classifier: Development Status :: 4 - Beta
Classifier: Intended Audience :: Developers
Classifier: Operating System :: OS Independent
Classifier: Programming Language :: Python :: 3
Classifier: Programming Language :: Python :: 3 :: Only
Classifier: Programming Language :: Python :: 3.12
Classifier: Programming Language :: Python :: 3.13
Classifier: Programming Language :: Python :: 3.14
Classifier: Topic :: Documentation
Classifier: Topic :: Software Development
Classifier: Topic :: Utilities
Classifier: Typing :: Typed
Requires-Python: >=3.12
Requires-Dist: typing-inspection>=0.4.0
